{
  "$schema_version": "1.0",
  "plan": {
    "id": "EG06",
    "slug": "hope-feels-delayed",
    "category": {
      "primary": "emotion-garden",
      "primary_label": "情緒花園",
      "secondary": "grief-disappointment",
      "secondary_label": "悲傷與失望"
    },
    "tags": [
      "悲傷",
      "失望",
      "盼望遲來",
      "哀哭",
      "安慰"
    ],
    "title": "當盼望遲遲沒有來到",
    "subtitle": "這七天會陪你走過失望和漫長等待，把心慢慢帶回神仍然在的地方。",
    "audience": {
      "life_stage": [
        "成年女性",
        "任何年齡"
      ],
      "emotional_state": [
        "悲傷",
        "失望",
        "流淚"
      ],
      "spiritual_stage": [
        "任何階段"
      ]
    },
    "goal": "這七天會陪你走過失望和漫長等待，把心慢慢帶回神仍然在的地方。",
    "duration_days": 7,
    "estimated_minutes_per_day": 7,
    "flow_template": "scripture → teaching → prayer → verse_wall",
    "scripture_translation": "和合本",
    "cover": {
      "color_primary": "#C9B8C9",
      "color_secondary": "#5A4255",
      "image_key": "cover_woman_quiet_garden_soft_rain_grief",
      "icon": "falling-leaf-circle"
    },
    "key_verses": [
      {
        "display": "詩篇 13:1-2",
        "book_code": "PSA",
        "chapter": 13,
        "verses": "1-2"
      },
      {
        "display": "羅馬書 15:13",
        "book_code": "ROM",
        "chapter": 15,
        "verses": "13"
      }
    ],
    "status": "published",
    "version": "1.0.0",
    "last_updated": "2026-05-02"
  },
  "days": [
    {
      "day": 1,
      "day_label": "第 1 天",
      "title": "我不需要先堅强，才能來見神",
      "estimated_minutes": 7,
      "sections": [
        {
          "type": "scripture_focus",
          "ui_hint": "card.verse_hero",
          "heading": "今日經文",
          "verse": {
            "display": "詩篇 13:1-2",
            "book_code": "PSA",
            "chapter": 13,
            "verses": "1-2",
            "translation": "和合本",
            "text": "耶和華啊，你忘記我要到幾時呢？要到永遠嗎？你掩面不顧我要到幾時呢？我心里籌算，終日愁苦，要到幾時呢？"
          }
        },
        {
          "type": "teaching",
          "ui_hint": "card.body_text",
          "heading": "讀經引導",
          "paragraphs": [
            "很多人進到悲傷里，第一個本能動作就是撐住。不是因為真的不痛，而是因為不知道除了撐住還能怎麼办。你可能要工作、照顧家里、回應別人，甚至還得安慰那些比你更先崩潰的人。慢慢地，你就很容易把“我還能運轉”誤當成“我已經沒那麼痛”。可事實上，能繼續生活和真的被安慰，是两回事。",
            "詩篇里有很多哀歌，是因為神早就知道，人不是只會在整齐時刻來見祂。人也會在混亂、失落、說不清楚、甚至有點怨的時候來見祂。詩篇 13 篇里的“要到幾時呢”，就是這樣一種禱告。它沒有先包装自己，也沒有先提醒自己“要積極一點”。它先把里面真實的痛喊出來。馬太福音說，哀恸的人有福了，因為他們必得安慰。換句話說，**神不是在等一個已經整理好的你，祂是在悲傷里的你開口時，就願意來安慰。**",
            "今天不是要你馬上明白一切，也不是要你趕快找到意義。今天只需要做一個動作：停止要求自己先堅强。來到神面前時，你可以帶着亂、帶着空、帶着眼淚，甚至帶着不知道該說什麼的沉默。禱告有時候不是一篇完整的話，而只是一個叹息：“主啊，我真的很累。”那也夠了。",
            "你也许可以在一個安靜角落里停五分鐘，把手放在心口，慢慢說：“主啊，我現在就是這樣來到你面前。”讓這一天成為哀悼的開始，而不是繼續表演沒事。"
          ]
        },
        {
          "type": "prayer",
          "ui_hint": "card.prayer",
          "heading": "禱告",
          "body": "主啊，我今天不想再要求自己先堅强，才來見你。你知道我外面還能運轉，里面却已經很累、很空、很痛。谢谢你沒有把哀哭的人推開，反而應许安慰。今天我就這樣來到你面前，沒有修飾，沒有包装，也不勉强自己馬上懂得一切。若我只能叹息，求你也聽見；若我只能流淚，求你也接住。奉耶穌的名禱告，阿們。",
          "audio_key": null
        },
        {
          "type": "verse_wall",
          "ui_hint": "card.verse_list",
          "heading": "今日經文",
          "verses": [
            {
              "display": "詩篇 13:1-2",
              "book_code": "PSA",
              "chapter": 13,
              "verses": "1-2",
              "translation": "和合本",
              "text": "耶和華啊，你忘記我要到幾時呢？要到永遠嗎？你掩面不顧我要到幾時呢？我心里籌算，終日愁苦，要到幾時呢？"
            },
            {
              "display": "馬太福音 5:4",
              "book_code": "MAT",
              "chapter": 5,
              "verses": "4",
              "translation": "和合本",
              "text": "哀恸的人有福了！因為他們必得安慰。"
            }
          ]
        }
      ]
    },
    {
      "day": 2,
      "day_label": "第 2 天",
      "title": "我真正失去的，到底是什麼",
      "estimated_minutes": 7,
      "sections": [
        {
          "type": "scripture_focus",
          "ui_hint": "card.verse_hero",
          "heading": "今日經文",
          "verse": {
            "display": "路得記 1:20-21",
            "book_code": "RUT",
            "chapter": 1,
            "verses": "20-21",
            "translation": "和合本",
            "text": "拿俄米對他們說：不要叫我拿俄米，要叫我瑪拉，因為全能者使我受了大苦。我滿滿地出去，耶和華使我空空地回來……"
          }
        },
        {
          "type": "teaching",
          "ui_hint": "card.body_text",
          "heading": "讀經引導",
          "paragraphs": [
            "悲傷常常不只是一件具體的失去，它里面還包着更深一层的东西。你也许表面上在難過一段關系結束了，可更深的失去可能是安全感；你表面上在難過機會沒了，可更深的失去可能是對自己的期待；你表面上在難過某個人離開了，可更深的失去可能是那種“有人懂我”的感覺。如果我們只停留在表面的事件，心里那塊更深的傷很容易繼續隱隱作痛。",
            "路得記里的拿俄米，不只是失去丈夫和兒子，她也失去原本熟悉的人生方向。她從“滿滿地出去”到“空空地回來”，這句話里面装着的不只是物質上的落差，更是身份、歸屬、盼望都被動搖的感覺。詩篇 42 篇里，詩人也不只是說自己忧悶，而是在忧悶里不斷追問自己的心。**很多時候，神医治的不是表面的一件事，而是那件事背後被一起扯裂的地方。**",
            "今天，試着把你的悲傷分两层來寫。第一层是“我失去了什麼”；第二层是“這讓我里面哪一部分也跟着失去了”。也许是信任、是安穩、是方向感、是被愛的篤定。這個分辨會幫助你更明白，為什麼有些痛不是時間一久就自動過去，因為它傷到的，從來不只是表面。",
            "當你能更真實地看見自己失去的是什麼，禱告也會開始变得更具體。你不只是求“主啊，安慰我”，你也會開始說：“主啊，我失去了安穩，求你把我心里面那個被扯開的地方帶回你面前。”"
          ]
        },
        {
          "type": "prayer",
          "ui_hint": "card.prayer",
          "heading": "禱告",
          "body": "主啊，求你幫助我更真實地看見自己的悲傷。很多時候我以為自己只是失去了一件事，可其實里面還有更深的部分跟着一起被扯開了。你知道我失去的是什麼，也知道那份失去怎樣動搖了我里面的安全感、歸屬感或對未來的想象。今天我把這些更深层的失落帶到你面前，求你不要只安慰表面的情緒，也請你進入我里面那些更難看見、却一直隱隱作痛的地方。谢谢你看見比我自己還深。讓我的認識和医治，都在你的光里慢慢發生。奉耶穌的名禱告，阿們。",
          "audio_key": null
        },
        {
          "type": "verse_wall",
          "ui_hint": "card.verse_list",
          "heading": "今日經文",
          "verses": [
            {
              "display": "路得記 1:20-21",
              "book_code": "RUT",
              "chapter": 1,
              "verses": "20-21",
              "translation": "和合本",
              "text": "拿俄米對他們說：不要叫我拿俄米，要叫我瑪拉，因為全能者使我受了大苦。我滿滿地出去，耶和華使我空空地回來……"
            },
            {
              "display": "詩篇 42:3,5",
              "book_code": "PSA",
              "chapter": 42,
              "verses": "3,5",
              "translation": "和合本",
              "text": "我昼夜以眼淚當飲食……我的心哪，你為何忧悶？"
            }
          ]
        }
      ]
    },
    {
      "day": 3,
      "day_label": "第 3 天",
      "title": "當等待本身也成了傷",
      "estimated_minutes": 7,
      "sections": [
        {
          "type": "scripture_focus",
          "ui_hint": "card.verse_hero",
          "heading": "今日經文",
          "verse": {
            "display": "箴言 13:12",
            "book_code": "PRO",
            "chapter": 13,
            "verses": "12",
            "translation": "和合本",
            "text": "所盼望的遲延未得，令人心忧；所願意的临到，却是生命樹。"
          }
        },
        {
          "type": "teaching",
          "ui_hint": "card.body_text",
          "heading": "讀經引導",
          "paragraphs": [
            "有些人悲傷，不是因為已經明確失去了什麼，而是因為一直在等，一直沒有結果。等待很特別，因為它沒有一個明顯的終點可以讓你哀悼，也沒有一個明確的句號可以讓你說“這件事結束了”。你只是一直活在半空里，不上不下，不知道該繼續盼望，還是該開始放下。這樣的状態，常常比一刀切的失去更磨人。",
            "箴言 13 章說，所盼望的遲延未得，令人心忧。聖經在這里承認，等待會傷心。不是只有坏消息才會讓人痛，長期沒有消息、沒有变化、沒有實現，也一樣會把人拖得很累。你可能明明什麼都還沒正式失去，却已經開始在心里一點點哀悼那個遲遲沒有來到的未來。**等待不是輕松的中間地帶，它本身也可能成為一處深傷。**",
            "詩篇 130 篇里，詩人說：“我的心等候主，勝於守夜的等候天亮。”這不是一種輕松的等候，而是一種在黑夜里帶着盼望的堅持。對很多失望中的人來說，這很真實。你不是已經放棄了，但你也真的很累。今天的重點不是强迫自己重新充滿熱情，而是承認：我等得很累。",
            "如果你最近也在一個漫長的不確定里，可以試試把等待具體化：你到底在等什麼？一個結果、一次回應、一段關系的轉機、一個遲遲沒發生的改变？把它說出來，然後求神不是只改变時間線，而是先在等待里扶住你。有些等待會讓人白天照常生活，夜里却突然很空，好像心總懸着落不下來。若你也是這樣，不必輕看這種累。把“我真的等累了”說給神聽，本身就已經是一種很深的禱告。"
          ]
        },
        {
          "type": "prayer",
          "ui_hint": "card.prayer",
          "heading": "禱告",
          "body": "主啊，我承認自己在等候里已經很累。不是每一種痛都來自明確的失去，有些痛來自長久沒有答案、沒有改变、沒有結果。你知道我卡在這種不上不下的感覺里多久了，也知道我有時连該繼續盼望還是該開始放下都分不清。今天我把這份等候里的疲惫帶到你面前。求你不要只看見我在等什麼，也看見等待本身怎樣傷了我。請在結果還沒有來到之前，先扶住我的心。奉耶穌的名禱告，阿們。",
          "audio_key": null
        },
        {
          "type": "verse_wall",
          "ui_hint": "card.verse_list",
          "heading": "今日經文",
          "verses": [
            {
              "display": "箴言 13:12",
              "book_code": "PRO",
              "chapter": 13,
              "verses": "12",
              "translation": "和合本",
              "text": "所盼望的遲延未得，令人心忧；所願意的临到，却是生命樹。"
            },
            {
              "display": "詩篇 130:5-6",
              "book_code": "PSA",
              "chapter": 130,
              "verses": "5-6",
              "translation": "和合本",
              "text": "我等候耶和華，我的心等候；我也仰望他的話。我的心等候主，勝於守夜的，等候天亮。"
            }
          ]
        }
      ]
    },
    {
      "day": 4,
      "day_label": "第 4 天",
      "title": "耶穌怎樣陪人走過哀傷",
      "estimated_minutes": 7,
      "sections": [
        {
          "type": "scripture_focus",
          "ui_hint": "card.verse_hero",
          "heading": "今日經文",
          "verse": {
            "display": "約翰福音 11:32-35",
            "book_code": "JHN",
            "chapter": 11,
            "verses": "32-35",
            "translation": "和合本",
            "text": "馬利亞到了耶穌那里，看見他，就俯伏在他腳前，說：主啊，你若早在這里，我兄弟必不死。耶穌看見她哭……就心里悲叹，又甚忧愁……耶穌哭了。"
          }
        },
        {
          "type": "teaching",
          "ui_hint": "card.body_text",
          "heading": "讀經引導",
          "paragraphs": [
            "有些人一悲傷，就會自動把神想成一個在旁邊看着的人，好像祂知道真理、知道結局、知道答案，但不一定真正進入人的感受。可福音書里的耶穌不是這樣。祂不是一個把道理先擺出來的主，祂是一個先靠近人的主。",
            "在拉撒路的故事里，耶穌沒有因為自己即将行神迹，就省略哀傷那一段。祂看見馬利亞哭，看見周圍的人哭，祂自己也哭了。這一點對悲傷中的人極其重要，因為它讓你知道，神並不會因為祂看得更遠，就要求你今天不要痛。希伯來書說，耶穌能體恤我們的軟弱，意思不是祂抽象地“理解”痛，而是祂在自己肉身里經歷過流淚、痛苦、被誤會和失去。**你現在所經歷的悲傷，不是耶穌無法触碰的領域。**",
            "這會改变我們怎麼來到主面前。你不需要先把自己整理成一個“比较屬靈的樣子”，才能禱告。你可以像馬利亞那樣帶着眼淚、帶着埋怨、帶着“主啊，你若早在這里”的痛來到祂面前。耶穌沒有因為這句話就遠離她，祂反而進入那一刻的悲傷。",
            "今天如果你覺得自己很難禱告，可以試試只默想這件事：主不是站在遠處要我快點過去，主是在我身邊陪我經過。讓這個畫面比你里面那個催促自己的聲音更有分量。也许你今天無法說很多話，那就只停在“耶穌哭了”這四個字上。那短短一句，已經足夠告訴你，神子不會輕看人的眼淚。祂的同在不是抽象的答案，而是能陪人穿過哀傷的真實安慰。"
          ]
        },
        {
          "type": "prayer",
          "ui_hint": "card.prayer",
          "heading": "禱告",
          "body": "主耶穌，谢谢你不是一個遠遠知道我痛的人，而是一位願意靠近我痛的人。你沒有因為自己知道更遠的結局，就繞過人當下的哀傷。今天求你讓我更真實地經歷你的靠近。若我心里還有埋怨、有不明白、有“你若早在這里”的痛，也求你不要因這些遠離我。讓我知道，我的悲傷不是你無法進入的地方。願你的同在先成為我的安慰，也讓我在你的溫柔里慢慢放下那個總在催促我快點恢復的聲音。並願我以後也更像你，懂得怎樣陪人走過哀傷。奉耶穌的名禱告，阿們。",
          "audio_key": null
        },
        {
          "type": "verse_wall",
          "ui_hint": "card.verse_list",
          "heading": "今日經文",
          "verses": [
            {
              "display": "約翰福音 11:32-35",
              "book_code": "JHN",
              "chapter": 11,
              "verses": "32-35",
              "translation": "和合本",
              "text": "馬利亞到了耶穌那里，看見他，就俯伏在他腳前，說：主啊，你若早在這里，我兄弟必不死。耶穌看見她哭……就心里悲叹，又甚忧愁……耶穌哭了。"
            },
            {
              "display": "希伯來書 4:15",
              "book_code": "HEB",
              "chapter": 4,
              "verses": "15",
              "translation": "和合本",
              "text": "因我們的大祭司並非不能體恤我們的軟弱……"
            }
          ]
        }
      ]
    },
    {
      "day": 5,
      "day_label": "第 5 天",
      "title": "讓身體和日常也參與恢復",
      "estimated_minutes": 7,
      "sections": [
        {
          "type": "scripture_focus",
          "ui_hint": "card.verse_hero",
          "heading": "今日經文",
          "verse": {
            "display": "詩篇 23:1-3",
            "book_code": "PSA",
            "chapter": 23,
            "verses": "1-3",
            "translation": "和合本",
            "text": "耶和華是我的牧者，我必不致缺乏。他使我躺卧在青草地上，領我在可安歇的水邊。他使我的靈魂甦醒。"
          }
        },
        {
          "type": "teaching",
          "ui_hint": "card.body_text",
          "heading": "讀經引導",
          "paragraphs": [
            "悲傷不只住在心里，它也會住進身體和日常里。你可能發現自己比以前更容易累，睡不安穩，胃口忽大忽小，明明沒做什麼却總像沒電。很多人面對這些反應時會先責怪自己：“我怎麼這麼沒用”“我怎麼连日常都過不好了”。但其實，失去和失望本來就會讓整個人都被影响。",
            "詩篇 23 篇里的神，不只是帶人明白道理的神，祂也是使人躺卧、領人到可安歇之處的牧者。列王紀上 19 章里，以利亞極度低落時，神先給他睡眠、食物和休息。這個次序非常重要，因為它提醒我們，屬靈恢復並不排斥身體照顧。**神医治你的時候，不只是医治你的“想法”，祂也在照顧你的身體和生活節奏。**",
            "如果你最近一直覺得自己沒力氣，不要急着把這全都解释成懒散或退步。你可以先問：我的身體現在最需要什麼？是更早一點休息，是吃一頓正常的飯，是走出去晒一會太陽，是先把讓你更焦慮的信息關掉，還是允许自己今天少做一點？這些動作本身不是全部答案，但它們是在告訴自己：我不是機器，我是一個正在哀悼、也值得被照顧的人。",
            "也许今天你願意留下一件很具體的照顧動作，不為效率，只為恢復。讓你的身體也參與這場神正在進行的安慰。也许只是早點洗澡上床，也许是把晚上的安排减掉一件，也许是吃一頓熱的食物，不邊看手機邊吞下去。這樣做不是逃避現實，而是在對自己說：神也在這里照顧我。悲傷中的恢復，往往就是從這些看似很小、却很誠實的照顧開始。"
          ]
        },
        {
          "type": "prayer",
          "ui_hint": "card.prayer",
          "heading": "禱告",
          "body": "主啊，求你幫助我不要輕看悲傷對我整個人的影响。你知道我最近的疲惫、睡不好、沒有胃口、提不起劲，也知道我很容易因為這些反應而責怪自己。谢谢你不是只關心我想得對不對，你也關心我有沒有被好好牧养。今天求你教我用一個更溫柔的眼光看待自己，也讓我願意接受休息、食物、安靜和照顧，不把這些當成軟弱。願你像牧者一樣，把我領到可安歇的地方，讓我的身心都在你里面一點一點甦醒。奉耶穌的名禱告，阿們。",
          "audio_key": null
        },
        {
          "type": "verse_wall",
          "ui_hint": "card.verse_list",
          "heading": "今日經文",
          "verses": [
            {
              "display": "詩篇 23:1-3",
              "book_code": "PSA",
              "chapter": 23,
              "verses": "1-3",
              "translation": "和合本",
              "text": "耶和華是我的牧者，我必不致缺乏。他使我躺卧在青草地上，領我在可安歇的水邊。他使我的靈魂甦醒。"
            },
            {
              "display": "列王紀上 19:5-8",
              "book_code": "1KI",
              "chapter": 19,
              "verses": "5-8",
              "translation": "和合本",
              "text": "他就躺在羅騰樹下，睡着了……起來吃吧！……他就起來吃了喝了，仗着這飲食的力，走了四十昼夜。"
            }
          ]
        }
      ]
    },
    {
      "day": 6,
      "day_label": "第 6 天",
      "title": "神仍能在破碎故事里做新事",
      "estimated_minutes": 7,
      "sections": [
        {
          "type": "scripture_focus",
          "ui_hint": "card.verse_hero",
          "heading": "今日經文",
          "verse": {
            "display": "路得記 1:20-21",
            "book_code": "RUT",
            "chapter": 1,
            "verses": "20-21",
            "translation": "和合本",
            "text": "拿俄米對他們說：不要叫我拿俄米，要叫我瑪拉，因為全能者使我受了大苦……"
          }
        },
        {
          "type": "teaching",
          "ui_hint": "card.body_text",
          "heading": "讀經引導",
          "paragraphs": [
            "走過一段失望之後，人很容易在心里下一個結論：我以後不要再那麼期待了，我不要再那麼認真了，我不要再把自己交出去那麼多了。這樣做可以暫時保護自己，可時間一長，心也會跟着慢慢封住。不是不痛了，而是你不再讓任何新的东西靠近。",
            "拿俄米在路得記里沒有假装自己沒事，她甚至直接說，不要再叫我拿俄米，要叫我瑪拉。她敢承認人生如今变苦了。可是神並沒有因為她的苦而停止工作。以賽亞書說：“看哪，我要做一件新事。”這不是要求人立刻忘記過去，也不是要你馬上看見結果。它更像是一句溫柔但堅定的提醒：**失望再深，也不代表神已經寫完你的故事。**",
            "很多時候，新事開始得很小。可能是一位突然願意認真聽你說話的朋友，可能是一個你終於重新開口的禱告，可能是你今天第一次不再把所有情緒都壓下去。不要輕看這些小小的開始，它們常常就是神在廢墟上重新動工的方式。",
            "今天你可以問神一句很簡單的話：“主啊，在我現在這片破碎里，你想讓我留意哪一個新的記號？”不需要急着自己製造答案，只要保持心是開着的。新事有時不會一下子很大，但它會是真的。也许你今天還不能說自己已經重新相信了，可你可以先保留一個小小的位置，不把人生的門完全關上。那一點點願意，就是神工作可以繼續進入的地方。"
          ]
        },
        {
          "type": "prayer",
          "ui_hint": "card.prayer",
          "heading": "禱告",
          "body": "主啊，我承認我有時已經不太敢期待新的东西了。受過傷之後，把心關起來似乎比较安全，可你知道那樣的安全也讓我越來越封閉。谢谢你沒有因為我的故事变苦，就停止在其中工作。求你幫助我相信，破碎不代表終點，失望也不代表你已經離開。讓我在還帶着傷的時候，仍然有一點點勇氣去留意你新的記號。若你正在很安靜地重新動工，求你也讓我有一顆願意被你重新打開的心。奉耶穌的名禱告，阿們。",
          "audio_key": null
        },
        {
          "type": "verse_wall",
          "ui_hint": "card.verse_list",
          "heading": "今日經文",
          "verses": [
            {
              "display": "路得記 1:20-21",
              "book_code": "RUT",
              "chapter": 1,
              "verses": "20-21",
              "translation": "和合本",
              "text": "拿俄米對他們說：不要叫我拿俄米，要叫我瑪拉，因為全能者使我受了大苦……"
            },
            {
              "display": "以賽亞書 43:18-19",
              "book_code": "ISA",
              "chapter": 43,
              "verses": "18-19",
              "translation": "和合本",
              "text": "你們不要記念從前的事……看哪，我要做一件新事；如今要發現，你們岂不知道嗎？"
            }
          ]
        }
      ]
    },
    {
      "day": 7,
      "day_label": "第 7 天",
      "title": "盼望可以慢慢回來",
      "estimated_minutes": 7,
      "sections": [
        {
          "type": "scripture_focus",
          "ui_hint": "card.verse_hero",
          "heading": "今日經文",
          "verse": {
            "display": "羅馬書 15:13",
            "book_code": "ROM",
            "chapter": 15,
            "verses": "13",
            "translation": "和合本",
            "text": "但願使人有盼望的神，因信将諸般的喜樂平安充滿你們的心，使你們借着聖靈的能力大有盼望。"
          }
        },
        {
          "type": "teaching",
          "ui_hint": "card.body_text",
          "heading": "讀經引導",
          "paragraphs": [
            "真正的恢復，很多時候不是某一天忽然覺得“我完全好了”，而是你開始一點一點願意再次向神打開。你也许還是會有触景傷情的時候，也许某些問題仍然沒有完全解開，也许偶爾還是會懷疑自己能不能真的再相信一次。可在這樣的不完全里，盼望依然可能慢慢回來。",
            "羅馬書 15 章稱神為“使人有盼望的神”。這句話很重要，因為它提醒我們，盼望不是靠自己硬挤出來的情緒，也不是靠勉强自己正面思考製造出來的状態。它更像是神親自放進人心里的一點點光。启示錄又說，神要擦去一切眼淚。這讓今天的傷有了未來，也讓今天的悲傷不會擁有最後解释權。**真正的盼望不是否認今天還有淚，而是知道眼淚不會永遠替我說最後一句話。**",
            "今天適合做一個結束動作：回顧這七天，寫下一句你最想帶進接下來生活里的提醒。可能是“神看見我”，也可能是“故事還沒有結束”，又或是“我可以慢慢恢復”。不要要求這句話立刻讓你完全改变，而是讓它成為你未來再被悲傷碰到時，可以回來抓住的一個小锚點。",
            "盼望有時不是轟轟烈烈地回來，而是像清晨第一點光，你還不能立刻看清所有东西，但你知道夜沒有一直做主。願這成為你繼續往前走的方式。将來某一天，你也许還是會突然被回忆碰到、被失落刺到；那並不表示這七天白走了，而只是提醒你仍然需要回到這位使人有盼望的神面前。盼望不是一次得到、永遠不再搖動，它更像你不斷回來的方向。"
          ]
        },
        {
          "type": "prayer",
          "ui_hint": "card.prayer",
          "heading": "禱告",
          "body": "主啊，谢谢你這七天沒有嫌我慢，也沒有因為我仍然會難過就離開我。求你把盼望輕輕放回我心里，不一定轟烈，不一定一下子讓我完全喜樂，但讓我知道，我仍然可以重新向你打開。谢谢你是使人有盼望的神，也是最終要擦去一切眼淚的神。願你把我從失望里一點一點領出來，讓我帶着新的溫柔、新的信靠、新的盼望繼續活下去。也求你使我領受的安慰，将來成為我安慰別人的器皿。奉耶穌的名禱告，阿們。",
          "audio_key": null
        },
        {
          "type": "verse_wall",
          "ui_hint": "card.verse_list",
          "heading": "今日經文",
          "verses": [
            {
              "display": "羅馬書 15:13",
              "book_code": "ROM",
              "chapter": 15,
              "verses": "13",
              "translation": "和合本",
              "text": "但願使人有盼望的神，因信将諸般的喜樂平安充滿你們的心，使你們借着聖靈的能力大有盼望。"
            },
            {
              "display": "启示錄 21:4",
              "book_code": "REV",
              "chapter": 21,
              "verses": "4",
              "translation": "和合本",
              "text": "神要擦去他們一切的眼淚；不再有死亡，也不再有悲哀、哭號、疼痛，因為以前的事都過去了。"
            }
          ]
        }
      ]
    }
  ]
}