{
  "verses": [
    {
      "verse": 1,
      "text": "亚萨向「以色列的牧者」祷告，求他发出光来、施展能力，叠句是「神啊，求你使我们回转……我们便要得救」。复兴必始于神。惟有他使我们回转归向他，我们才得救。"
    },
    {
      "verse": 2,
      "text": "亚萨向「以色列的牧者」祷告，求他发出光来、施展能力，叠句是「神啊，求你使我们回转……我们便要得救」。复兴必始于神。惟有他使我们回转归向他，我们才得救。"
    },
    {
      "verse": 3,
      "text": "亚萨向「以色列的牧者」祷告，求他发出光来、施展能力，叠句是「神啊，求你使我们回转……我们便要得救」。复兴必始于神。惟有他使我们回转归向他，我们才得救。"
    },
    {
      "verse": 4,
      "text": "神向他子民的祷告发怒、以眼泪当食物，要到几时呢？他再求「万军之神啊，求你使我们回转」。叠句更加迫切。反复的祷告，向神求他独能赐下的更新。"
    },
    {
      "verse": 5,
      "text": "神向他子民的祷告发怒、以眼泪当食物，要到几时呢？他再求「万军之神啊，求你使我们回转」。叠句更加迫切。反复的祷告，向神求他独能赐下的更新。"
    },
    {
      "verse": 6,
      "text": "神向他子民的祷告发怒、以眼泪当食物，要到几时呢？他再求「万军之神啊，求你使我们回转」。叠句更加迫切。反复的祷告，向神求他独能赐下的更新。"
    },
    {
      "verse": 7,
      "text": "神向他子民的祷告发怒、以眼泪当食物，要到几时呢？他再求「万军之神啊，求你使我们回转」。叠句更加迫切。反复的祷告，向神求他独能赐下的更新。"
    },
    {
      "verse": 8,
      "text": "他追念神怎样「从埃及挪出一棵葡萄树」，栽种、使它满地、伸展到海。以色列是他亲手所栽。神曾以慈爱看顾他的子民。"
    },
    {
      "verse": 9,
      "text": "他追念神怎样「从埃及挪出一棵葡萄树」，栽种、使它满地、伸展到海。以色列是他亲手所栽。神曾以慈爱看顾他的子民。"
    },
    {
      "verse": 10,
      "text": "他追念神怎样「从埃及挪出一棵葡萄树」，栽种、使它满地、伸展到海。以色列是他亲手所栽。神曾以慈爱看顾他的子民。"
    },
    {
      "verse": 11,
      "text": "他追念神怎样「从埃及挪出一棵葡萄树」，栽种、使它满地、伸展到海。以色列是他亲手所栽。神曾以慈爱看顾他的子民。"
    },
    {
      "verse": 12,
      "text": "神为何拆毁它的篱笆，任过路人摘取、野猪践踏呢？葡萄园暴露无遮。神一撤去保护，他的子民就敞露于败亡。"
    },
    {
      "verse": 13,
      "text": "神为何拆毁它的篱笆，任过路人摘取、野猪践踏呢？葡萄园暴露无遮。神一撤去保护，他的子民就敞露于败亡。"
    },
    {
      "verse": 14,
      "text": "「万军之神啊，求你回转……眷顾这葡萄树」，它被火焚、被砍。他恳求神回来。荒废的葡萄园惟一的指望，是看守者的归回。"
    },
    {
      "verse": 15,
      "text": "「万军之神啊，求你回转……眷顾这葡萄树」，它被火焚、被砍。他恳求神回来。荒废的葡萄园惟一的指望，是看守者的归回。"
    },
    {
      "verse": 16,
      "text": "「万军之神啊，求你回转……眷顾这葡萄树」，它被火焚、被砍。他恳求神回来。荒废的葡萄园惟一的指望，是看守者的归回。"
    },
    {
      "verse": 17,
      "text": "他求神的手扶持「你右手所栽的人子」，并誓言他们必不退后；末了再次「耶和华万军之神啊，求你使我们回转，使你的脸发光」。三叠的叠句结束这诗。得救就是神向我们转脸、我们向他回转。"
    },
    {
      "verse": 18,
      "text": "他求神的手扶持「你右手所栽的人子」，并誓言他们必不退后；末了再次「耶和华万军之神啊，求你使我们回转，使你的脸发光」。三叠的叠句结束这诗。得救就是神向我们转脸、我们向他回转。"
    },
    {
      "verse": 19,
      "text": "他求神的手扶持「你右手所栽的人子」，并誓言他们必不退后；末了再次「耶和华万军之神啊，求你使我们回转，使你的脸发光」。三叠的叠句结束这诗。得救就是神向我们转脸、我们向他回转。"
    }
  ]
}