{
  "verses": [
    {
      "verse": 1,
      "text": "以撒叫了雅各來，再一次給他祝福——這一回沒有欺哄。他打發他往巴旦亞蘭母親的本家去娶妻：不可娶迦南女子。這約必須娶進約裡。"
    },
    {
      "verse": 2,
      "text": "以撒叫了雅各來，再一次給他祝福——這一回沒有欺哄。他打發他往巴旦亞蘭母親的本家去娶妻：不可娶迦南女子。這約必須娶進約裡。"
    },
    {
      "verse": 3,
      "text": "願全能的神賜福給你，使你生養眾多，將亞伯拉罕的福賜給你，使你承受你所寄居的地。如今這祝福是明明白白地流向那「對」的兒子。以撒已經接受了神一向所說的。"
    },
    {
      "verse": 4,
      "text": "願全能的神賜福給你，使你生養眾多，將亞伯拉罕的福賜給你，使你承受你所寄居的地。如今這祝福是明明白白地流向那「對」的兒子。以撒已經接受了神一向所說的。"
    },
    {
      "verse": 5,
      "text": "以撒打發雅各走，他往巴旦亞蘭去，到母舅拉班那裡。那欺哄人的，開始在另一個欺哄人手下，受他漫長的磨鍊。"
    },
    {
      "verse": 6,
      "text": "以掃看在眼裡。他見迦南女子使父親不喜悅，就往以實瑪利家去，在原有的妻子之外，又娶了以實瑪利的女兒瑪哈拉。這是討好以撒的半吊子努力——拿娶妻來擺平一段關係的難處。這樣的樣式，延續到了又一代。"
    },
    {
      "verse": 7,
      "text": "以掃看在眼裡。他見迦南女子使父親不喜悅，就往以實瑪利家去，在原有的妻子之外，又娶了以實瑪利的女兒瑪哈拉。這是討好以撒的半吊子努力——拿娶妻來擺平一段關係的難處。這樣的樣式，延續到了又一代。"
    },
    {
      "verse": 8,
      "text": "以掃看在眼裡。他見迦南女子使父親不喜悅，就往以實瑪利家去，在原有的妻子之外，又娶了以實瑪利的女兒瑪哈拉。這是討好以撒的半吊子努力——拿娶妻來擺平一段關係的難處。這樣的樣式，延續到了又一代。"
    },
    {
      "verse": 9,
      "text": "以掃看在眼裡。他見迦南女子使父親不喜悅，就往以實瑪利家去，在原有的妻子之外，又娶了以實瑪利的女兒瑪哈拉。這是討好以撒的半吊子努力——拿娶妻來擺平一段關係的難處。這樣的樣式，延續到了又一代。"
    },
    {
      "verse": 10,
      "text": "雅各離開別是巴，往哈蘭去。日落時，他到了一個地方——創世記後面才點出地名，此刻不過是「某處」。他拿石頭當枕頭躺下。一個逃亡的人，睡在地上。"
    },
    {
      "verse": 11,
      "text": "雅各離開別是巴，往哈蘭去。日落時，他到了一個地方——創世記後面才點出地名，此刻不過是「某處」。他拿石頭當枕頭躺下。一個逃亡的人，睡在地上。"
    },
    {
      "verse": 12,
      "text": "他夢見一個梯子立在地上，梯子的頭頂著天，有神的使者在梯子上上去下來。兩個世界，並不如我們所想的那樣隔絕。其間有往來川流不息。"
    },
    {
      "verse": 13,
      "text": "耶和華站在梯子以上：我是你祖亞伯拉罕的神，也是以撒的神。你現在所躺的地，我要賜給你和你的後裔。這親密的約，如今指名認領了雅各。"
    },
    {
      "verse": 14,
      "text": "你的後裔必像地上的塵沙，向四方開展。地上萬族必因你和你的後裔得福。那曾對亞伯拉罕所說的應許，如今竟澆在這逃命的欺哄者身上。"
    },
    {
      "verse": 15,
      "text": "我也與你同在，你無論往哪裡去，我必保佑你，領你歸回這地。我總不離棄你，直到成全了我對你所應許的。這是恩典臨到一個連一個字都不配得的人。"
    },
    {
      "verse": 16,
      "text": "雅各睡醒了，說：「耶和華真在這裡，我竟不知道！」列祖的神原來一直就在近旁；這逃亡的人，只是從前沒有察覺。"
    },
    {
      "verse": 17,
      "text": "他就懼怕，說：這地方何等可畏！這不是別的，乃是神的殿，也是天的門。神聖的實在，忽然比頭頂的夜空更加鮮明。"
    },
    {
      "verse": 18,
      "text": "雅各清早起來，把所枕的石頭立作柱子，澆油在上頭。他標記這地方——睡覺之處，變作了敬拜之處。"
    },
    {
      "verse": 19,
      "text": "他給那地方起名叫伯特利——「神的殿」——那城原先名叫路斯。他所起的名留住了，舊名大多被人忘了。與神的相遇，使萬事改了名。"
    },
    {
      "verse": 20,
      "text": "雅各許願：神若與我同在，在路上保佑我，賜我食物衣服，使我平平安安回來——耶和華就必作我的神，這石頭必作神的殿，凡神所賜我的，我必將十分之一獻給他。他頭一個禱告，半是講條件，半是信心。神兩樣都收下，並使之生長。"
    },
    {
      "verse": 21,
      "text": "雅各許願：神若與我同在，在路上保佑我，賜我食物衣服，使我平平安安回來——耶和華就必作我的神，這石頭必作神的殿，凡神所賜我的，我必將十分之一獻給他。他頭一個禱告，半是講條件，半是信心。神兩樣都收下，並使之生長。"
    },
    {
      "verse": 22,
      "text": "雅各許願：神若與我同在，在路上保佑我，賜我食物衣服，使我平平安安回來——耶和華就必作我的神，這石頭必作神的殿，凡神所賜我的，我必將十分之一獻給他。他頭一個禱告，半是講條件，半是信心。神兩樣都收下，並使之生長。"
    }
  ]
}