{
  "verses": [
    {
      "verse": 1,
      "text": "在哥林多保罗与亚居拉、百基拉同住，一同织帐棚。做工的使徒。他一面传道，一面亲手劳力。"
    },
    {
      "verse": 2,
      "text": "在哥林多保罗与亚居拉、百基拉同住，一同织帐棚。做工的使徒。他一面传道，一面亲手劳力。"
    },
    {
      "verse": 3,
      "text": "在哥林多保罗与亚居拉、百基拉同住，一同织帐棚。做工的使徒。他一面传道，一面亲手劳力。"
    },
    {
      "verse": 4,
      "text": "他们抗拒时，「你们的罪归到你们自己头上……我往外邦人那里去」。清白的良心。他转向那肯听的人。"
    },
    {
      "verse": 5,
      "text": "他们抗拒时，「你们的罪归到你们自己头上……我往外邦人那里去」。清白的良心。他转向那肯听的人。"
    },
    {
      "verse": 6,
      "text": "他们抗拒时，「你们的罪归到你们自己头上……我往外邦人那里去」。清白的良心。他转向那肯听的人。"
    },
    {
      "verse": 7,
      "text": "许多哥林多人信而受洗。哥林多的果子。福音在罪恶之城扎根。"
    },
    {
      "verse": 8,
      "text": "许多哥林多人信而受洗。哥林多的果子。福音在罪恶之城扎根。"
    },
    {
      "verse": 9,
      "text": "主说「不要怕……在这城里我有许多的百姓」；他住了一年半。得鼓励。神的应许坚固他的仆人。"
    },
    {
      "verse": 10,
      "text": "主说「不要怕……在这城里我有许多的百姓」；他住了一年半。得鼓励。神的应许坚固他的仆人。"
    },
    {
      "verse": 11,
      "text": "主说「不要怕……在这城里我有许多的百姓」；他住了一年半。得鼓励。神的应许坚固他的仆人。"
    },
    {
      "verse": 12,
      "text": "犹太人把保罗带到迦流面前控告他。被拖上公堂。他们想以律法对付福音。"
    },
    {
      "verse": 13,
      "text": "犹太人把保罗带到迦流面前控告他。被拖上公堂。他们想以律法对付福音。"
    },
    {
      "verse": 14,
      "text": "迦流「都不管」，就把他们赶出去。撤案。神藉一个漠不关心的官拦阻仇敌。"
    },
    {
      "verse": 15,
      "text": "迦流「都不管」，就把他们赶出去。撤案。神藉一个漠不关心的官拦阻仇敌。"
    },
    {
      "verse": 16,
      "text": "迦流「都不管」，就把他们赶出去。撤案。神藉一个漠不关心的官拦阻仇敌。"
    },
    {
      "verse": 17,
      "text": "迦流「都不管」，就把他们赶出去。撤案。神藉一个漠不关心的官拦阻仇敌。"
    },
    {
      "verse": 18,
      "text": "保罗许过愿，带亚居拉、百基拉往叙利亚去。不停脚步。使徒不住地往来服事。"
    },
    {
      "verse": 19,
      "text": "保罗许过愿，带亚居拉、百基拉往叙利亚去。不停脚步。使徒不住地往来服事。"
    },
    {
      "verse": 20,
      "text": "他走遍加拉太、弗吕家「坚固众门徒」。建立。他重访各教会，使他们坚立。"
    },
    {
      "verse": 21,
      "text": "他走遍加拉太、弗吕家「坚固众门徒」。建立。他重访各教会，使他们坚立。"
    },
    {
      "verse": 22,
      "text": "他走遍加拉太、弗吕家「坚固众门徒」。建立。他重访各教会，使他们坚立。"
    },
    {
      "verse": 23,
      "text": "他走遍加拉太、弗吕家「坚固众门徒」。建立。他重访各教会，使他们坚立。"
    },
    {
      "verse": 24,
      "text": "亚波罗「有学问，最能讲解圣经」，却只晓得约翰的洗；亚居拉、百基拉「将……更加详细」地讲给他。谦卑受教。有恩赐的人也乐意多学。"
    },
    {
      "verse": 25,
      "text": "亚波罗「有学问，最能讲解圣经」，却只晓得约翰的洗；亚居拉、百基拉「将……更加详细」地讲给他。谦卑受教。有恩赐的人也乐意多学。"
    },
    {
      "verse": 26,
      "text": "亚波罗「有学问，最能讲解圣经」，却只晓得约翰的洗；亚居拉、百基拉「将……更加详细」地讲给他。谦卑受教。有恩赐的人也乐意多学。"
    },
    {
      "verse": 27,
      "text": "他大大帮助弟兄，「有力地驳倒犹太人……证明耶稣是基督」。有力的传道。他的学问服事福音。"
    },
    {
      "verse": 28,
      "text": "他大大帮助弟兄，「有力地驳倒犹太人……证明耶稣是基督」。有力的传道。他的学问服事福音。"
    }
  ]
}