{
  "verses": [
    {
      "verse": 1,
      "text": "Sansón halla a su mujer dada a otro y busca venganza. Agraviado. Es provocado."
    },
    {
      "verse": 2,
      "text": "Sansón halla a su mujer dada a otro y busca venganza. Agraviado. Es provocado."
    },
    {
      "verse": 3,
      "text": "Sansón halla a su mujer dada a otro y busca venganza. Agraviado. Es provocado."
    },
    {
      "verse": 4,
      "text": "Quema las mieses de los filisteos con zorras y teas. Quemadas. Paga su agravio."
    },
    {
      "verse": 5,
      "text": "Quema las mieses de los filisteos con zorras y teas. Quemadas. Paga su agravio."
    },
    {
      "verse": 6,
      "text": "Ellos queman a su mujer; él los hiere y mora en una peña. Vengado. La violencia engendra violencia."
    },
    {
      "verse": 7,
      "text": "Ellos queman a su mujer; él los hiere y mora en una peña. Vengado. La violencia engendra violencia."
    },
    {
      "verse": 8,
      "text": "Ellos queman a su mujer; él los hiere y mora en una peña. Vengado. La violencia engendra violencia."
    },
    {
      "verse": 9,
      "text": "Judá lo ata para entregarlo a los filisteos. Atado. Sus propios hermanos temen."
    },
    {
      "verse": 10,
      "text": "Judá lo ata para entregarlo a los filisteos. Atado. Sus propios hermanos temen."
    },
    {
      "verse": 11,
      "text": "Judá lo ata para entregarlo a los filisteos. Atado. Sus propios hermanos temen."
    },
    {
      "verse": 12,
      "text": "Judá lo ata para entregarlo a los filisteos. Atado. Sus propios hermanos temen."
    },
    {
      "verse": 13,
      "text": "Judá lo ata para entregarlo a los filisteos. Atado. Sus propios hermanos temen."
    },
    {
      "verse": 14,
      "text": "Las cuerdas se rompen; mata a mil con una quijada. Quijada. Dios salva por un arma humilde."
    },
    {
      "verse": 15,
      "text": "Las cuerdas se rompen; mata a mil con una quijada. Quijada. Dios salva por un arma humilde."
    },
    {
      "verse": 16,
      "text": "Las cuerdas se rompen; mata a mil con una quijada. Quijada. Dios salva por un arma humilde."
    },
    {
      "verse": 17,
      "text": "Las cuerdas se rompen; mata a mil con una quijada. Quijada. Dios salva por un arma humilde."
    },
    {
      "verse": 18,
      "text": "Sediento, ora; Dios le da agua; juzga veinte años. Agua. Dios responde su clamor."
    },
    {
      "verse": 19,
      "text": "Sediento, ora; Dios le da agua; juzga veinte años. Agua. Dios responde su clamor."
    },
    {
      "verse": 20,
      "text": "Sediento, ora; Dios le da agua; juzga veinte años. Agua. Dios responde su clamor."
    }
  ]
}