{"verses":[{"verse":1,"text":"誰 如智慧人呢？誰 知道 事情 的解釋呢？人 的智慧 使他的臉 發光，並使他臉上 的暴氣 改變。"},{"verse":2,"text":"我 勸你遵守 王 的命令；既指 神 起誓，理當如此。"},{"verse":3,"text":"不要 急躁 離開 王的面前，不要 固執 行惡，因為 他凡事 都隨自己的心意 而行。"},{"verse":4,"text":"王 的話 本有權力，誰 敢問他 說「你做 甚麼」呢？"},{"verse":5,"text":"凡遵守 命令的，必不 經歷 禍患；智慧人 的心 能辨明 時候和定理（原文是審判；下節同）。"},{"verse":6,"text":"各樣 事務 成就都有 時候 和定理，因為 人 的苦難 重壓 在他身上。"},{"verse":7,"text":"他不 知道 將來的事，因為 將來 如何，誰 能告訴 他呢？"},{"verse":8,"text":"無 人 有權力掌管 生命，將 生命 留住；也無人 有權力掌管 死 期；這場爭戰，無人 能免；邪惡 也不能 救 那好行邪惡的人。"},{"verse":9,"text":"這 一切 我都見過，也專 心 查考日光 之下 所 做 的一切 事。有時 這人 管轄 那人，令人 受害。"},{"verse":10,"text":"我見 惡人 埋葬，歸入墳墓；又見行正直事的 離開 聖 地，在城中 被人忘記。這 也 是虛空。"},{"verse":11,"text":"因為 斷定 罪名 不 立刻 施刑，所以 世人 滿 心 作 惡。"},{"verse":12,"text":"罪人 雖然 作 惡 百次，倒享長久的年日；然而 我 準 知道， 敬畏 神的，就是 在他面前 敬畏的人，終久必得 福樂。"},{"verse":13,"text":"惡人 卻不 得 福樂，也不 得長久的 年日；這年日好像影兒，因 他不 敬畏 神。"},{"verse":14,"text":"世上 有 一件虛空的事，就是 義人 所 遭遇的，反照惡人 所行的；又有 惡人 所遭遇的，反照義人 所行的。我說，這 也是 虛空。"},{"verse":15,"text":"我 就稱讚 快樂，原來 人 在日光 之下，莫 強 如 吃 喝 快樂；因為他 在日光 之下， 神 賜 他 一生 的年日，要從勞碌中，時常享受所得的。"},{"verse":16,"text":"我專 心 求 智慧，要看 世上 所 做 的事。（有晝 夜 不睡覺 不 合眼的。）"},{"verse":17,"text":"我就看明 神 一切的 作為， 知道人 查 不 出 日光 之下 所 做 的事； 任憑 他 費多少力 尋查，都查不 出來，就是 智慧人 雖想 知道，也是 查不 出來。"}]}