{
  "verses": [
    {
      "verse": 1,
      "text": "但以理读耶利米书，明白七十年之数，就「禁食……披麻蒙灰，定意向主神祈祷恳求」。圣经激发祷告。神的应许催敬虔人寻求其成就。"
    },
    {
      "verse": 2,
      "text": "但以理读耶利米书，明白七十年之数，就「禁食……披麻蒙灰，定意向主神祈祷恳求」。圣经激发祷告。神的应许催敬虔人寻求其成就。"
    },
    {
      "verse": 3,
      "text": "但以理读耶利米书，明白七十年之数，就「禁食……披麻蒙灰，定意向主神祈祷恳求」。圣经激发祷告。神的应许催敬虔人寻求其成就。"
    },
    {
      "verse": 4,
      "text": "他认罪说「主啊，大而可畏的神……我们犯了罪」，没有听从众先知。诚实的认罪。真祷告承认那招来审判的罪。"
    },
    {
      "verse": 5,
      "text": "他认罪说「主啊，大而可畏的神……我们犯了罪」，没有听从众先知。诚实的认罪。真祷告承认那招来审判的罪。"
    },
    {
      "verse": 6,
      "text": "他认罪说「主啊，大而可畏的神……我们犯了罪」，没有听从众先知。诚实的认罪。真祷告承认那招来审判的罪。"
    },
    {
      "verse": 7,
      "text": "「主啊，你是公义的，我们是脸上蒙羞」；然而「怜悯赦免都归主」。神公义又怜悯。痛悔的人从神的公义逃向他的怜悯。"
    },
    {
      "verse": 8,
      "text": "「主啊，你是公义的，我们是脸上蒙羞」；然而「怜悯赦免都归主」。神公义又怜悯。痛悔的人从神的公义逃向他的怜悯。"
    },
    {
      "verse": 9,
      "text": "「主啊，你是公义的，我们是脸上蒙羞」；然而「怜悯赦免都归主」。神公义又怜悯。痛悔的人从神的公义逃向他的怜悯。"
    },
    {
      "verse": 10,
      "text": "因他们不顺从，咒诅倾倒；神借这大灾证实了他的话。话语应验。即使在审判中，神也证明自己信守警告。"
    },
    {
      "verse": 11,
      "text": "因他们不顺从，咒诅倾倒；神借这大灾证实了他的话。话语应验。即使在审判中，神也证明自己信守警告。"
    },
    {
      "verse": 12,
      "text": "因他们不顺从，咒诅倾倒；神借这大灾证实了他的话。话语应验。即使在审判中，神也证明自己信守警告。"
    },
    {
      "verse": 13,
      "text": "这一切灾祸临到，他们仍不祷告转离罪孽；「耶和华我们的神是公义的」。迟迟不悔。但以理为神辩白，为国的刚硬哀伤。"
    },
    {
      "verse": 14,
      "text": "这一切灾祸临到，他们仍不祷告转离罪孽；「耶和华我们的神是公义的」。迟迟不悔。但以理为神辩白，为国的刚硬哀伤。"
    },
    {
      "verse": 15,
      "text": "这一切灾祸临到，他们仍不祷告转离罪孽；「耶和华我们的神是公义的」。迟迟不悔。但以理为神辩白，为国的刚硬哀伤。"
    },
    {
      "verse": 16,
      "text": "他恳求转离向耶路撒冷的怒气；「主啊，求你垂听，求你赦免……不要迟延」，因城是称为你名下的。恳切的代求。他以神自己的荣耀为根基祈求。"
    },
    {
      "verse": 17,
      "text": "他恳求转离向耶路撒冷的怒气；「主啊，求你垂听，求你赦免……不要迟延」，因城是称为你名下的。恳切的代求。他以神自己的荣耀为根基祈求。"
    },
    {
      "verse": 18,
      "text": "他恳求转离向耶路撒冷的怒气；「主啊，求你垂听，求你赦免……不要迟延」，因城是称为你名下的。恳切的代求。他以神自己的荣耀为根基祈求。"
    },
    {
      "verse": 19,
      "text": "他恳求转离向耶路撒冷的怒气；「主啊，求你垂听，求你赦免……不要迟延」，因城是称为你名下的。恳切的代求。他以神自己的荣耀为根基祈求。"
    },
    {
      "verse": 20,
      "text": "他正祷告认罪时，加百列「迅速飞来」，在献晚祭时按手在他身上。祷告蒙应。心一真诚寻求神，天上就动。"
    },
    {
      "verse": 21,
      "text": "他正祷告认罪时，加百列「迅速飞来」，在献晚祭时按手在他身上。祷告蒙应。心一真诚寻求神，天上就动。"
    },
    {
      "verse": 22,
      "text": "加百列说他来使他明白，因「你初恳求时，就发出命令」。蒙爱蒙听。神毫不迟延地答他祷告的仆人。"
    },
    {
      "verse": 23,
      "text": "加百列说他来使他明白，因「你初恳求时，就发出命令」。蒙爱蒙听。神毫不迟延地答他祷告的仆人。"
    },
    {
      "verse": 24,
      "text": "「为你本国之民……已经定了七十个七，要止住罪过……引进永义。」伟大的预言。一切都指向弥赛亚的工作。"
    },
    {
      "verse": 25,
      "text": "从出令到「受膏君」有六十九个七；然后「那受膏者必被剪除，一无所有」。预言十架。基督受死非为自己的罪，乃为我们。"
    },
    {
      "verse": 26,
      "text": "从出令到「受膏君」有六十九个七；然后「那受膏者必被剪除，一无所有」。预言十架。基督受死非为自己的罪，乃为我们。"
    },
    {
      "verse": 27,
      "text": "他必与许多人坚定盟约，「使祭祀……止息」。祭祀得成全。基督的死，终止了一切别的祭物的需要。"
    }
  ]
}