{
  "verses": [
    {
      "verse": 1,
      "text": "「王的心在耶和华手中，好像陇沟的水随意流转」；人所行的自以为正，神却衡量人心；「行仁义公平，比献祭更蒙耶和华悦纳」。神连君王也掌管。他看重公义过于仪式。"
    },
    {
      "verse": 2,
      "text": "「王的心在耶和华手中，好像陇沟的水随意流转」；人所行的自以为正，神却衡量人心；「行仁义公平，比献祭更蒙耶和华悦纳」。神连君王也掌管。他看重公义过于仪式。"
    },
    {
      "verse": 3,
      "text": "「王的心在耶和华手中，好像陇沟的水随意流转」；人所行的自以为正，神却衡量人心；「行仁义公平，比献祭更蒙耶和华悦纳」。神连君王也掌管。他看重公义过于仪式。"
    },
    {
      "verse": 4,
      "text": "高傲的眼、骄傲的心都是罪；殷勤人的筹划足致丰裕，急躁却致缺乏；用谎言得的财是虚空，恶人的强暴必毁灭自己。骄傲贪婪败坏人。神赐福殷勤，倾覆不义之财。"
    },
    {
      "verse": 5,
      "text": "高傲的眼、骄傲的心都是罪；殷勤人的筹划足致丰裕，急躁却致缺乏；用谎言得的财是虚空，恶人的强暴必毁灭自己。骄傲贪婪败坏人。神赐福殷勤，倾覆不义之财。"
    },
    {
      "verse": 6,
      "text": "高傲的眼、骄傲的心都是罪；殷勤人的筹划足致丰裕，急躁却致缺乏；用谎言得的财是虚空，恶人的强暴必毁灭自己。骄傲贪婪败坏人。神赐福殷勤，倾覆不义之财。"
    },
    {
      "verse": 7,
      "text": "高傲的眼、骄傲的心都是罪；殷勤人的筹划足致丰裕，急躁却致缺乏；用谎言得的财是虚空，恶人的强暴必毁灭自己。骄傲贪婪败坏人。神赐福殷勤，倾覆不义之财。"
    },
    {
      "verse": 8,
      "text": "负罪人的路偏邪，清洁人的工却正直；宁住房顶的角，不与争吵的妇人同住；恶人的心专求恶，毫无怜悯。平安宝贵。恶人连对邻舍也专图恶事。"
    },
    {
      "verse": 9,
      "text": "负罪人的路偏邪，清洁人的工却正直；宁住房顶的角，不与争吵的妇人同住；恶人的心专求恶，毫无怜悯。平安宝贵。恶人连对邻舍也专图恶事。"
    },
    {
      "verse": 10,
      "text": "负罪人的路偏邪，清洁人的工却正直；宁住房顶的角，不与争吵的妇人同住；恶人的心专求恶，毫无怜悯。平安宝贵。恶人连对邻舍也专图恶事。"
    },
    {
      "verse": 11,
      "text": "亵慢人受罚，愚蒙人就得智慧；义人留心察看恶人的家；「塞耳不听穷人哀求的，他将来呼吁也不蒙应允」。怜悯是必需的。漠视困苦人，就断送自己的呼求。"
    },
    {
      "verse": 12,
      "text": "亵慢人受罚，愚蒙人就得智慧；义人留心察看恶人的家；「塞耳不听穷人哀求的，他将来呼吁也不蒙应允」。怜悯是必需的。漠视困苦人，就断送自己的呼求。"
    },
    {
      "verse": 13,
      "text": "亵慢人受罚，愚蒙人就得智慧；义人留心察看恶人的家；「塞耳不听穷人哀求的，他将来呼吁也不蒙应允」。怜悯是必需的。漠视困苦人，就断送自己的呼求。"
    },
    {
      "verse": 14,
      "text": "暗中送的礼物止息怒气；公平施行时，义人喜乐，作孽的却惊恐；偏离通达之道的，必住在阴魂的会中。公平使敬虔人欢喜。离开智慧，就漂向死亡。"
    },
    {
      "verse": 15,
      "text": "暗中送的礼物止息怒气；公平施行时，义人喜乐，作孽的却惊恐；偏离通达之道的，必住在阴魂的会中。公平使敬虔人欢喜。离开智慧，就漂向死亡。"
    },
    {
      "verse": 16,
      "text": "暗中送的礼物止息怒气；公平施行时，义人喜乐，作孽的却惊恐；偏离通达之道的，必住在阴魂的会中。公平使敬虔人欢喜。离开智慧，就漂向死亡。"
    },
    {
      "verse": 17,
      "text": "爱宴乐、酒、油的，必不富足；恶人成了义人的赎价；宁住旷野，不与争吵使气的妇人同住。放纵使人贫穷。独居的平安胜过家中的争闹。"
    },
    {
      "verse": 18,
      "text": "爱宴乐、酒、油的，必不富足；恶人成了义人的赎价；宁住旷野，不与争吵使气的妇人同住。放纵使人贫穷。独居的平安胜过家中的争闹。"
    },
    {
      "verse": 19,
      "text": "爱宴乐、酒、油的，必不富足；恶人成了义人的赎价；宁住旷野，不与争吵使气的妇人同住。放纵使人贫穷。独居的平安胜过家中的争闹。"
    },
    {
      "verse": 20,
      "text": "智慧人家中积存珍宝与膏油，愚昧人却挥霍尽净；追求公义仁慈的，得着生命与尊荣；「智慧人爬上勇士的城」。智慧既存又胜。追求公义带来生命。"
    },
    {
      "verse": 21,
      "text": "智慧人家中积存珍宝与膏油，愚昧人却挥霍尽净；追求公义仁慈的，得着生命与尊荣；「智慧人爬上勇士的城」。智慧既存又胜。追求公义带来生命。"
    },
    {
      "verse": 22,
      "text": "智慧人家中积存珍宝与膏油，愚昧人却挥霍尽净；追求公义仁慈的，得着生命与尊荣；「智慧人爬上勇士的城」。智慧既存又胜。追求公义带来生命。"
    },
    {
      "verse": 23,
      "text": "「谨守口与舌的，就保守自己免受灾难」；骄傲亵慢的行事暴怒；「懒惰人的心愿将他害死，因他手不肯做工」。要守住舌头。空想而不做工，害死懒惰人。"
    },
    {
      "verse": 24,
      "text": "「谨守口与舌的，就保守自己免受灾难」；骄傲亵慢的行事暴怒；「懒惰人的心愿将他害死，因他手不肯做工」。要守住舌头。空想而不做工，害死懒惰人。"
    },
    {
      "verse": 25,
      "text": "「谨守口与舌的，就保守自己免受灾难」；骄傲亵慢的行事暴怒；「懒惰人的心愿将他害死，因他手不肯做工」。要守住舌头。空想而不做工，害死懒惰人。"
    },
    {
      "verse": 26,
      "text": "贪婪的终日贪求，义人却施舍不吝；「恶人献祭，为耶和华所憎恶」；作假见证的必灭亡，肯听的人却所言长存。慷慨是义人的记号。神厌弃恶心所献的敬拜。"
    },
    {
      "verse": 27,
      "text": "贪婪的终日贪求，义人却施舍不吝；「恶人献祭，为耶和华所憎恶」；作假见证的必灭亡，肯听的人却所言长存。慷慨是义人的记号。神厌弃恶心所献的敬拜。"
    },
    {
      "verse": 28,
      "text": "贪婪的终日贪求，义人却施舍不吝；「恶人献祭，为耶和华所憎恶」；作假见证的必灭亡，肯听的人却所言长存。慷慨是义人的记号。神厌弃恶心所献的敬拜。"
    },
    {
      "verse": 29,
      "text": "恶人脸无羞耻，正直人却谨慎己路；没有智慧能敌挡耶和华；「马是为打仗之日预备的，得胜乃在乎耶和华」。预备是智慧，得胜却属神。无人的计谋能胜过他。"
    },
    {
      "verse": 30,
      "text": "恶人脸无羞耻，正直人却谨慎己路；没有智慧能敌挡耶和华；「马是为打仗之日预备的，得胜乃在乎耶和华」。预备是智慧，得胜却属神。无人的计谋能胜过他。"
    },
    {
      "verse": 31,
      "text": "恶人脸无羞耻，正直人却谨慎己路；没有智慧能敌挡耶和华；「马是为打仗之日预备的，得胜乃在乎耶和华」。预备是智慧，得胜却属神。无人的计谋能胜过他。"
    }
  ]
}