{
  "verses": [
    {
      "verse": 1,
      "text": "「王的心在耶和華手中，好像隴溝的水隨意流轉」；人所行的自以為正，神卻衡量人心；「行仁義公平，比獻祭更蒙耶和華悅納」。神連君王也掌管。他看重公義過於儀式。"
    },
    {
      "verse": 2,
      "text": "「王的心在耶和華手中，好像隴溝的水隨意流轉」；人所行的自以為正，神卻衡量人心；「行仁義公平，比獻祭更蒙耶和華悅納」。神連君王也掌管。他看重公義過於儀式。"
    },
    {
      "verse": 3,
      "text": "「王的心在耶和華手中，好像隴溝的水隨意流轉」；人所行的自以為正，神卻衡量人心；「行仁義公平，比獻祭更蒙耶和華悅納」。神連君王也掌管。他看重公義過於儀式。"
    },
    {
      "verse": 4,
      "text": "高傲的眼、驕傲的心都是罪；殷勤人的籌劃足致豐裕，急躁卻致缺乏；用謊言得的財是虛空，惡人的強暴必毀滅自己。驕傲貪婪敗壞人。神賜福殷勤，傾覆不義之財。"
    },
    {
      "verse": 5,
      "text": "高傲的眼、驕傲的心都是罪；殷勤人的籌劃足致豐裕，急躁卻致缺乏；用謊言得的財是虛空，惡人的強暴必毀滅自己。驕傲貪婪敗壞人。神賜福殷勤，傾覆不義之財。"
    },
    {
      "verse": 6,
      "text": "高傲的眼、驕傲的心都是罪；殷勤人的籌劃足致豐裕，急躁卻致缺乏；用謊言得的財是虛空，惡人的強暴必毀滅自己。驕傲貪婪敗壞人。神賜福殷勤，傾覆不義之財。"
    },
    {
      "verse": 7,
      "text": "高傲的眼、驕傲的心都是罪；殷勤人的籌劃足致豐裕，急躁卻致缺乏；用謊言得的財是虛空，惡人的強暴必毀滅自己。驕傲貪婪敗壞人。神賜福殷勤，傾覆不義之財。"
    },
    {
      "verse": 8,
      "text": "負罪人的路偏邪，清潔人的工卻正直；寧住房頂的角，不與爭吵的婦人同住；惡人的心專求惡，毫無憐憫。平安寶貴。惡人連對鄰舍也專圖惡事。"
    },
    {
      "verse": 9,
      "text": "負罪人的路偏邪，清潔人的工卻正直；寧住房頂的角，不與爭吵的婦人同住；惡人的心專求惡，毫無憐憫。平安寶貴。惡人連對鄰舍也專圖惡事。"
    },
    {
      "verse": 10,
      "text": "負罪人的路偏邪，清潔人的工卻正直；寧住房頂的角，不與爭吵的婦人同住；惡人的心專求惡，毫無憐憫。平安寶貴。惡人連對鄰舍也專圖惡事。"
    },
    {
      "verse": 11,
      "text": "褻慢人受罰，愚蒙人就得智慧；義人留心察看惡人的家；「塞耳不聽窮人哀求的，他將來呼籲也不蒙應允」。憐憫是必需的。漠視困苦人，就斷送自己的呼求。"
    },
    {
      "verse": 12,
      "text": "褻慢人受罰，愚蒙人就得智慧；義人留心察看惡人的家；「塞耳不聽窮人哀求的，他將來呼籲也不蒙應允」。憐憫是必需的。漠視困苦人，就斷送自己的呼求。"
    },
    {
      "verse": 13,
      "text": "褻慢人受罰，愚蒙人就得智慧；義人留心察看惡人的家；「塞耳不聽窮人哀求的，他將來呼籲也不蒙應允」。憐憫是必需的。漠視困苦人，就斷送自己的呼求。"
    },
    {
      "verse": 14,
      "text": "暗中送的禮物止息怒氣；公平施行時，義人喜樂，作孽的卻驚恐；偏離通達之道的，必住在陰魂的會中。公平使敬虔人歡喜。離開智慧，就漂向死亡。"
    },
    {
      "verse": 15,
      "text": "暗中送的禮物止息怒氣；公平施行時，義人喜樂，作孽的卻驚恐；偏離通達之道的，必住在陰魂的會中。公平使敬虔人歡喜。離開智慧，就漂向死亡。"
    },
    {
      "verse": 16,
      "text": "暗中送的禮物止息怒氣；公平施行時，義人喜樂，作孽的卻驚恐；偏離通達之道的，必住在陰魂的會中。公平使敬虔人歡喜。離開智慧，就漂向死亡。"
    },
    {
      "verse": 17,
      "text": "愛宴樂、酒、油的，必不富足；惡人成了義人的贖價；寧住曠野，不與爭吵使氣的婦人同住。放縱使人貧窮。獨居的平安勝過家中的爭鬧。"
    },
    {
      "verse": 18,
      "text": "愛宴樂、酒、油的，必不富足；惡人成了義人的贖價；寧住曠野，不與爭吵使氣的婦人同住。放縱使人貧窮。獨居的平安勝過家中的爭鬧。"
    },
    {
      "verse": 19,
      "text": "愛宴樂、酒、油的，必不富足；惡人成了義人的贖價；寧住曠野，不與爭吵使氣的婦人同住。放縱使人貧窮。獨居的平安勝過家中的爭鬧。"
    },
    {
      "verse": 20,
      "text": "智慧人家中積存珍寶與膏油，愚昧人卻揮霍盡淨；追求公義仁慈的，得著生命與尊榮；「智慧人爬上勇士的城」。智慧既存又勝。追求公義帶來生命。"
    },
    {
      "verse": 21,
      "text": "智慧人家中積存珍寶與膏油，愚昧人卻揮霍盡淨；追求公義仁慈的，得著生命與尊榮；「智慧人爬上勇士的城」。智慧既存又勝。追求公義帶來生命。"
    },
    {
      "verse": 22,
      "text": "智慧人家中積存珍寶與膏油，愚昧人卻揮霍盡淨；追求公義仁慈的，得著生命與尊榮；「智慧人爬上勇士的城」。智慧既存又勝。追求公義帶來生命。"
    },
    {
      "verse": 23,
      "text": "「謹守口與舌的，就保守自己免受災難」；驕傲褻慢的行事暴怒；「懶惰人的心願將他害死，因他手不肯做工」。要守住舌頭。空想而不做工，害死懶惰人。"
    },
    {
      "verse": 24,
      "text": "「謹守口與舌的，就保守自己免受災難」；驕傲褻慢的行事暴怒；「懶惰人的心願將他害死，因他手不肯做工」。要守住舌頭。空想而不做工，害死懶惰人。"
    },
    {
      "verse": 25,
      "text": "「謹守口與舌的，就保守自己免受災難」；驕傲褻慢的行事暴怒；「懶惰人的心願將他害死，因他手不肯做工」。要守住舌頭。空想而不做工，害死懶惰人。"
    },
    {
      "verse": 26,
      "text": "貪婪的終日貪求，義人卻施捨不吝；「惡人獻祭，為耶和華所憎惡」；作假見證的必滅亡，肯聽的人卻所言長存。慷慨是義人的記號。神厭棄噁心所獻的敬拜。"
    },
    {
      "verse": 27,
      "text": "貪婪的終日貪求，義人卻施捨不吝；「惡人獻祭，為耶和華所憎惡」；作假見證的必滅亡，肯聽的人卻所言長存。慷慨是義人的記號。神厭棄噁心所獻的敬拜。"
    },
    {
      "verse": 28,
      "text": "貪婪的終日貪求，義人卻施捨不吝；「惡人獻祭，為耶和華所憎惡」；作假見證的必滅亡，肯聽的人卻所言長存。慷慨是義人的記號。神厭棄噁心所獻的敬拜。"
    },
    {
      "verse": 29,
      "text": "惡人臉無羞恥，正直人卻謹慎己路；沒有智慧能敵擋耶和華；「馬是為打仗之日預備的，得勝乃在乎耶和華」。預備是智慧，得勝卻屬神。無人的計謀能勝過他。"
    },
    {
      "verse": 30,
      "text": "惡人臉無羞恥，正直人卻謹慎己路；沒有智慧能敵擋耶和華；「馬是為打仗之日預備的，得勝乃在乎耶和華」。預備是智慧，得勝卻屬神。無人的計謀能勝過他。"
    },
    {
      "verse": 31,
      "text": "惡人臉無羞恥，正直人卻謹慎己路；沒有智慧能敵擋耶和華；「馬是為打仗之日預備的，得勝乃在乎耶和華」。預備是智慧，得勝卻屬神。無人的計謀能勝過他。"
    }
  ]
}