{"verses":[{"verse":1,"text":"第五位 天使 吹号，我就 看见 一个星 从 天 落到 地 上， 有无底 坑 的钥匙 赐给 它。"},{"verse":2,"text":"它开了 无底 坑，便有 烟 从 坑里 往上冒，好像 大 火炉 的烟； 日头 和 天空 都因 这烟 昏暗了。"},{"verse":3,"text":"有蝗虫 从 烟 中出来，飞到地 上； 有能力 赐给 牠们，好像 地上 蝎子 的 能力一样，"},{"verse":4,"text":"并且 吩咐 牠们说，不可 伤害 地上 的草 和 各样 青物，并 一切 树木，惟独 要伤害 额 上 没 有 神 印记 的人。"},{"verse":5,"text":"但 不 许 蝗虫 害死 他们，只叫 他们受痛苦 五个 月。 这 痛苦 就像 蝎子 螫 人 的痛苦一样。"},{"verse":6,"text":"在 那些 日子，人 要求 死， 决不 得 死； 愿意 死， 死 却远避 他们。"},{"verse":7,"text":"蝗虫的 形状，好像 预备 出战的 马一样， 头 上 戴的好像 金 冠冕， 脸面 好像 男人的 脸面，"},{"verse":8,"text":"头发 像 女人 的头发， 牙齿 像 狮子的牙齿。"},{"verse":9,"text":"胸前有 甲，好像 铁 甲。 牠们 翅膀 的声音，好像 许多 车 马 奔跑 上 阵 的声音。"},{"verse":10,"text":"有 尾巴 像 蝎子， 尾巴 上 的毒钩 能 伤 人 五个 月。"},{"verse":11,"text":"有 无底坑的 使者 作 牠们的 王，按着希伯来话， 名叫 亚巴顿， 希腊话， 名叫 亚玻伦。"},{"verse":12,"text":"第一样 灾祸 过去了， 还有 两样 灾祸 要来。"},{"verse":13,"text":"第六位 天使 吹号， 我就听见 有 声音 从 神 面前 金 坛 的四 角出来，"},{"verse":14,"text":"吩咐那吹 号 的第六位 天使，说：「把那 捆绑 在 幼发拉底 大 河 的四个 使者 释放了。」"},{"verse":15,"text":"那四个 使者 就被释放；他们 原是预备好了，到 某年 某月 某日 某时，要 杀 人 的三分之一。"},{"verse":16,"text":"马军 有二万万； 他们的 数目 我听见了。"},{"verse":17,"text":"我在异象 中 看见 那些马 和 骑 马的，骑马的胸前有 甲 如火，与 紫玛瑙 并 硫磺。 马 的头 好像 狮子 头， 有火、 有烟、 有硫磺 从 马的 口中 出来。"},{"verse":18,"text":"口中 所出来 的 火 与 烟 并 硫磺， 这 三样 灾 杀了 人 的三分之一。"},{"verse":19,"text":"这马 的能力 是 在 口 里 和 尾巴 上；因 这 尾巴 像 蛇，并且有 头 用以 害人。"},{"verse":20,"text":"其余 未曾 被 这些 灾 所杀 的人 仍旧不 悔改 自己 手 所做的，还是 去拜 鬼魔 和 那些 不 能 看、不能 听、不能 走，金、 银、 铜、 木、 石 的偶像，"},{"verse":21,"text":"又 不 悔改 他们 那些凶杀、 邪术、 奸淫、 偷窃的事。"}]}