{
  "verses": [
    {
      "verse": 1,
      "text": "法利賽人責門徒不洗手吃飯，拘守「古人的遺傳」。人造的規條。他們看重自己的習俗，過於神的律法。"
    },
    {
      "verse": 2,
      "text": "法利賽人責門徒不洗手吃飯，拘守「古人的遺傳」。人造的規條。他們看重自己的習俗，過於神的律法。"
    },
    {
      "verse": 3,
      "text": "法利賽人責門徒不洗手吃飯，拘守「古人的遺傳」。人造的規條。他們看重自己的習俗，過於神的律法。"
    },
    {
      "verse": 4,
      "text": "法利賽人責門徒不洗手吃飯，拘守「古人的遺傳」。人造的規條。他們看重自己的習俗，過於神的律法。"
    },
    {
      "verse": 5,
      "text": "「你們是離棄神的誡命，拘守人的遺傳」；這百姓用嘴唇尊敬，心卻遠離。空洞的敬拜。遺傳能擠掉真實的順服。"
    },
    {
      "verse": 6,
      "text": "「你們是離棄神的誡命，拘守人的遺傳」；這百姓用嘴唇尊敬，心卻遠離。空洞的敬拜。遺傳能擠掉真實的順服。"
    },
    {
      "verse": 7,
      "text": "「你們是離棄神的誡命，拘守人的遺傳」；這百姓用嘴唇尊敬，心卻遠離。空洞的敬拜。遺傳能擠掉真實的順服。"
    },
    {
      "verse": 8,
      "text": "「你們是離棄神的誡命，拘守人的遺傳」；這百姓用嘴唇尊敬，心卻遠離。空洞的敬拜。遺傳能擠掉真實的順服。"
    },
    {
      "verse": 9,
      "text": "他們以「各耳板」免人孝敬父母，「廢了神的道」。狡猾的規避。宗教的藉口，取消不了本分。"
    },
    {
      "verse": 10,
      "text": "他們以「各耳板」免人孝敬父母，「廢了神的道」。狡猾的規避。宗教的藉口，取消不了本分。"
    },
    {
      "verse": 11,
      "text": "他們以「各耳板」免人孝敬父母，「廢了神的道」。狡猾的規避。宗教的藉口，取消不了本分。"
    },
    {
      "verse": 12,
      "text": "他們以「各耳板」免人孝敬父母，「廢了神的道」。狡猾的規避。宗教的藉口，取消不了本分。"
    },
    {
      "verse": 13,
      "text": "他們以「各耳板」免人孝敬父母，「廢了神的道」。狡猾的規避。宗教的藉口，取消不了本分。"
    },
    {
      "verse": 14,
      "text": "從外面進去的不能汙穢人，惟有從裡面出來的才能。真正的源頭。罪出於心，不在乎手。"
    },
    {
      "verse": 15,
      "text": "從外面進去的不能汙穢人，惟有從裡面出來的才能。真正的源頭。罪出於心，不在乎手。"
    },
    {
      "verse": 16,
      "text": "從外面進去的不能汙穢人，惟有從裡面出來的才能。真正的源頭。罪出於心，不在乎手。"
    },
    {
      "verse": 17,
      "text": "入肚的終必排出，汙穢不了心；他這樣說，是指各樣食物都潔淨。身外之物。食物觸不到人的內心。"
    },
    {
      "verse": 18,
      "text": "入肚的終必排出，汙穢不了心；他這樣說，是指各樣食物都潔淨。身外之物。食物觸不到人的內心。"
    },
    {
      "verse": 19,
      "text": "入肚的終必排出，汙穢不了心；他這樣說，是指各樣食物都潔淨。身外之物。食物觸不到人的內心。"
    },
    {
      "verse": 20,
      "text": "從心裡發出惡念、兇殺、姦淫、驕傲，這才汙穢人。心的流溢。汙穢生於內裡，不在外面。"
    },
    {
      "verse": 21,
      "text": "從心裡發出惡念、兇殺、姦淫、驕傲，這才汙穢人。心的流溢。汙穢生於內裡，不在外面。"
    },
    {
      "verse": 22,
      "text": "從心裡發出惡念、兇殺、姦淫、驕傲，這才汙穢人。心的流溢。汙穢生於內裡，不在外面。"
    },
    {
      "verse": 23,
      "text": "從心裡發出惡念、兇殺、姦淫、驕傲，這才汙穢人。心的流溢。汙穢生於內裡，不在外面。"
    },
    {
      "verse": 24,
      "text": "一敘利腓尼基的希臘婦人，為被鬼附的女兒求他。堅持的懇求。一個外邦母親，尋求以色列之主的憐憫。"
    },
    {
      "verse": 25,
      "text": "一敘利腓尼基的希臘婦人，為被鬼附的女兒求他。堅持的懇求。一個外邦母親，尋求以色列之主的憐憫。"
    },
    {
      "verse": 26,
      "text": "一敘利腓尼基的希臘婦人，為被鬼附的女兒求他。堅持的懇求。一個外邦母親，尋求以色列之主的憐憫。"
    },
    {
      "verse": 27,
      "text": "先讓兒女吃飽；她答，狗也吃碎渣；「因這句話」鬼就出去了。謙卑的信。她卑微緊抓的信，贏得祝福。"
    },
    {
      "verse": 28,
      "text": "先讓兒女吃飽；她答，狗也吃碎渣；「因這句話」鬼就出去了。謙卑的信。她卑微緊抓的信，贏得祝福。"
    },
    {
      "verse": 29,
      "text": "先讓兒女吃飽；她答，狗也吃碎渣；「因這句話」鬼就出去了。謙卑的信。她卑微緊抓的信，贏得祝福。"
    },
    {
      "verse": 30,
      "text": "先讓兒女吃飽；她答，狗也吃碎渣；「因這句話」鬼就出去了。謙卑的信。她卑微緊抓的信，贏得祝福。"
    },
    {
      "verse": 31,
      "text": "有人帶耳聾舌結的人來；他嘆息，摸他，說「以法大，開了吧」。溫柔的看顧。他親切而個別地對待受苦的人。"
    },
    {
      "verse": 32,
      "text": "有人帶耳聾舌結的人來；他嘆息，摸他，說「以法大，開了吧」。溫柔的看顧。他親切而個別地對待受苦的人。"
    },
    {
      "verse": 33,
      "text": "有人帶耳聾舌結的人來；他嘆息，摸他，說「以法大，開了吧」。溫柔的看顧。他親切而個別地對待受苦的人。"
    },
    {
      "verse": 34,
      "text": "有人帶耳聾舌結的人來；他嘆息，摸他，說「以法大，開了吧」。溫柔的看顧。他親切而個別地對待受苦的人。"
    },
    {
      "verse": 35,
      "text": "他的耳開了、舌鬆了；雖被囑咐不要張揚，眾人卻傳開「他所做的都好」。滿溢的讚美。憐憫無法被隱藏。"
    },
    {
      "verse": 36,
      "text": "他的耳開了、舌鬆了；雖被囑咐不要張揚，眾人卻傳開「他所做的都好」。滿溢的讚美。憐憫無法被隱藏。"
    },
    {
      "verse": 37,
      "text": "他的耳開了、舌鬆了；雖被囑咐不要張揚，眾人卻傳開「他所做的都好」。滿溢的讚美。憐憫無法被隱藏。"
    }
  ]
}